[
  {
    "title": "सुपेला घड़ी चौक पर मात्र 55 लाख में दूकान उपलब्ध",
    "description": "G. E. रोड से 2nd उत्तर गंगोत्री के होजरी मार्केट की मेन लाइन में",
    "mainImageUrl": "https://divya0319.github.io/forSale/1/1.jpeg"
  },
  {
    "title": "कैलाश नगर एकता चौक के पास मात्र 15 लाख में रेडी मकान उपलब्ध",
    "description": "लोहिया निवास के पास प्राइम लोकेशन में",
    "mainImageUrl": "https://divya0319.github.io/forSale/2/1.jpeg"
  },
  {
    "title": "नेहरू नगर भिलाई से राजनांदगाव बाईपास मेन रोड रसमड़ा में मात्र 299 रु. प्रति वर्गफीट में 13000 sqrft. का प्लाट उपलब्ध",
    "description": "नेहरूनगर चौक से D मार्ट वाली बायपास मेन रोड रसमढ़ा में",
    "mainImageUrl": "https://divya0319.github.io/forSale/3/1.jpeg"
  }
]